CHANGES
LICENSE
MANIFEST.in
README.rst
setup.py
docs/README
docs/conf.py
docs/filelist.rst
docs/filemanagement.rst
docs/index.rst
docs/oauth.rst
docs/pydrive.rst
docs/quickstart.rst
docs/build/doctrees/filelist.doctree
docs/build/doctrees/filemanagement.doctree
docs/build/doctrees/index.doctree
docs/build/doctrees/oauth.doctree
docs/build/doctrees/pydrive.doctree
docs/build/doctrees/quickstart.doctree
docs/build/html/.buildinfo
docs/build/html/filelist.html
docs/build/html/filemanagement.html
docs/build/html/genindex.html
docs/build/html/index.html
docs/build/html/oauth.html
docs/build/html/objects.inv
docs/build/html/py-modindex.html
docs/build/html/pydrive.html
docs/build/html/quickstart.html
docs/build/html/search.html
docs/build/html/searchindex.js
docs/build/html/_sources/filelist.txt
docs/build/html/_sources/filemanagement.txt
docs/build/html/_sources/index.txt
docs/build/html/_sources/oauth.txt
docs/build/html/_sources/pydrive.txt
docs/build/html/_sources/quickstart.txt
docs/build/html/_static/ajax-loader.gif
docs/build/html/_static/basic.css
docs/build/html/_static/comment-bright.png
docs/build/html/_static/comment-close.png
docs/build/html/_static/comment.png
docs/build/html/_static/doctools.js
docs/build/html/_static/down-pressed.png
docs/build/html/_static/down.png
docs/build/html/_static/file.png
docs/build/html/_static/jquery-1.11.1.js
docs/build/html/_static/jquery.js
docs/build/html/_static/minus.png
docs/build/html/_static/plus.png
docs/build/html/_static/pygments.css
docs/build/html/_static/searchtools.js
docs/build/html/_static/underscore-1.3.1.js
docs/build/html/_static/underscore.js
docs/build/html/_static/up-pressed.png
docs/build/html/_static/up.png
docs/build/html/_static/websupport.js
docs/build/html/_static/css/badge_only.css
docs/build/html/_static/css/theme.css
docs/build/html/_static/fonts/Inconsolata-Bold.ttf
docs/build/html/_static/fonts/Inconsolata-Regular.ttf
docs/build/html/_static/fonts/Lato-Bold.ttf
pydriveziead.egg-info/PKG-INFO
pydriveziead.egg-info/SOURCES.txt
pydriveziead.egg-info/dependency_links.txt
pydriveziead.egg-info/requires.txt
pydriveziead.egg-info/top_level.txt