Metadata-Version: 2.1
Name: pydriveziead
Version: 1.3.1
Summary: easy.
Home-page: https://github.com/zieadshabkalieh/pydriveziead
Author: ZSK
Author-email: zshabkalieh@gmail.com
License: LICENSE
Platform: UNKNOWN
License-File: LICENSE
